brackettree/__init__.py
brackettree/clscomp.py
brackettree/nodes.py
brackettree-0.2.5.dist-info/LICENCE
brackettree-0.2.5.dist-info/METADATA
brackettree-0.2.5.dist-info/WHEEL
brackettree-0.2.5.dist-info/top_level.txt
brackettree-0.2.5.dist-info/RECORD
